{"Rh//14IBO8jhdaD+7Vf4uw==":"tpf%20logo%20-%20screen%20grab-222x128.png","c5zIWfiRqjFAdKeru2NcAQ==":"tpf%20icon-244x128.png","iBlqYrg5gTSuiXQDa7a4Qw==":"mbr-2000x3000.jpg","nXmBQaeCVtFxhGM1UVjB4Q==":"tpf%20logo%20-%20screen%20grab-128x73.png","cXNot6UZI7EHP2+5xepcFQ==":"fold-2000x1490.jpg","wjxcOIkBnk5gGBm0cBviWw==":"foil-2000x1982.jpg","dsYctxgW4vp+VkCEVJWiSg==":"fold-2000x2000.jpg","rWev1b4AJZRIEhNV8TPihQ==":"fold-1-2000x2000.jpg","ROIOih3bbYjjIi98UeHxEA==":"perf-pic-2000x1500.jpg","yNue7b2NPCdMM+I4wqgf/g==":"image04-2000x1326.jpg","Ols485c2gxPCSI7uH7250g==":"mbr-2000x1333.jpg","EnDbSprSsw4v8N6WF3Kqew==":"mbr-2000x1250.jpg"}